FernetKeyGen/SaltManager.py
FernetKeyGen/__init__.py
FernetKeyGen/main.py
fernetkeygen-1.0.2.dist-info/METADATA
fernetkeygen-1.0.2.dist-info/WHEEL
fernetkeygen-1.0.2.dist-info/top_level.txt
fernetkeygen-1.0.2.dist-info/RECORD
