Metadata-Version: 2.4
Name: FernetKeyGen
Version: 1.0.2
Requires-Python: >=3.11
Requires-Dist: cffi>=1.17.1
Requires-Dist: cryptography>=45.0.5
Requires-Dist: pycparser>=2.22
Provides-Extra: dev
Requires-Dist: pytest>=7.0.0; extra == "dev"
